LICENSE
MANIFEST.in
README.md
README.rst
requirements.txt
setup.py
mac.egg-info/PKG-INFO
mac.egg-info/SOURCES.txt
mac.egg-info/dependency_links.txt
mac.egg-info/entry_points.txt
mac.egg-info/requires.txt
mac.egg-info/top_level.txt
maccli/__init__.py
maccli/command_cli.py
maccli/config.py
maccli/interactive.py
maccli/mac_cli.py
maccli/parser_cli.py
maccli/dao/__init__.py
maccli/dao/api_auth.py
maccli/dao/api_configuration.py
maccli/dao/api_infrastructure.py
maccli/dao/api_instance.py
maccli/dao/api_provider.py
maccli/dao/api_resource.py
maccli/dao/inheritance.py
maccli/facade/__init__.py
maccli/facade/macfile.py
maccli/helper/__init__.py
maccli/helper/cmd.py
maccli/helper/exception.py
maccli/helper/http.py
maccli/helper/macfile.py
maccli/helper/metadata.py
maccli/helper/network.py
maccli/helper/simplecache.py
maccli/helper/unsortable.py
maccli/lib/ aliases.py
maccli/lib/__init__.py
maccli/service/__init__.py
maccli/service/auth.py
maccli/service/configuration.py
maccli/service/infrastructure.py
maccli/service/instance.py
maccli/service/macfile.py
maccli/service/provider.py
maccli/service/resource.py
maccli/view/__init__.py
maccli/view/view_cookbook.py
maccli/view/view_generic.py
maccli/view/view_hardware.py
maccli/view/view_infrastructure.py
maccli/view/view_instance.py
maccli/view/view_location.py
maccli/view/view_resource.py
tests/__init__.py
tests/mock_data.py
tests/test_api.py
tests/test_auth.py
tests/test_cli_command_cli.py
tests/test_cli_mac_cli.py
tests/test_dao_api_configuration.py
tests/test_dao_api_instance.py
tests/test_dao_api_provider.py
tests/test_facade_macfile.py
tests/test_helper_cmd.py
tests/test_helper_macfile.py
tests/test_helper_metadata_resources.py
tests/test_helper_network.py
tests/test_helper_unsortable.py
tests/test_instance.py
tests/test_parser_cli.py
tests/test_service_configuration.py
tests/test_service_infrastructure.py
tests/test_service_inheritance.py
tests/test_service_instance.py
tests/test_service_macfile.py
tests/test_service_provider.py
tests/test_service_resources.py
tests/test_view_view_infrastructures.py
tests/test_view_view_instances.py
tests/test_view_view_resources.py