Metadata-Version: 2.1
Name: mac
Version: 1.0.8
Summary: Technology agnostic orchestration framework
Home-page: https://manageacloud.com
Author: Manageacloud Services Pty LTD
Author-email: support@manageacloud.com
License: Apache v2
Keywords: manageacloud environment infrastructure deployment blue green docker puppet chef saltstack ansible bash rackspace aws digitalocean azuregce google compute engine multicloud multi-cloud orchestration ci cd continuous integration delivery deployment a/b testing
Platform: UNKNOWN
Classifier: Development Status :: 5 - Production/Stable
Classifier: Environment :: Console
Classifier: Intended Audience :: Developers
Classifier: Intended Audience :: System Administrators
Classifier: Intended Audience :: Information Technology
Classifier: Intended Audience :: Science/Research
Classifier: License :: OSI Approved :: Apache Software License
Classifier: Operating System :: POSIX
Classifier: Programming Language :: Python
